safegif/processFrames.py
safegif/test.py
SafeGIF-0.1.0.dist-info/LICENSE
SafeGIF-0.1.0.dist-info/METADATA
SafeGIF-0.1.0.dist-info/WHEEL
SafeGIF-0.1.0.dist-info/top_level.txt
SafeGIF-0.1.0.dist-info/RECORD
