Metadata-Version: 2.1
Name: SafeGIF
Version: 0.1.0
Summary: A Python package to scan GIFs for safety for people with photosensitive epilepsy.
Home-page: https://github.com/grajan22/safe-gif-scanner
Author: Gaia Rajan
Author-email: grajan22@andover.edu
License: MIT
Platform: UNKNOWN
Classifier: Development Status :: 1 - Planning
Classifier: Intended Audience :: Science/Research
Classifier: License :: OSI Approved :: BSD License
Classifier: Operating System :: POSIX :: Linux
Classifier: Programming Language :: Python :: 2
Classifier: Programming Language :: Python :: 2.7
Classifier: Programming Language :: Python :: 3
Classifier: Programming Language :: Python :: 3.4
Classifier: Programming Language :: Python :: 3.5
